README.md
pyproject.toml
setup.py
co6co.permissions.egg-info/PKG-INFO
co6co.permissions.egg-info/SOURCES.txt
co6co.permissions.egg-info/dependency_links.txt
co6co.permissions.egg-info/requires.txt
co6co.permissions.egg-info/top_level.txt
co6co.permissions.egg-info/zip-safe
co6co_permissions/__init__.py
co6co_permissions/api/__init__.py
co6co_permissions/api/config.py
co6co_permissions/api/dict.py
co6co_permissions/api/file.py
co6co_permissions/api/menu.py
co6co_permissions/api/resource.py
co6co_permissions/api/role.py
co6co_permissions/api/user.py
co6co_permissions/api/userGroup.py
co6co_permissions/api/verify.py
co6co_permissions/api/view.py
co6co_permissions/configs/__init__.py
co6co_permissions/configs/captcha.py
co6co_permissions/model/__init__.py
co6co_permissions/model/enum/__init__.py
co6co_permissions/model/filters/__init__.py
co6co_permissions/model/filters/config_filter.py
co6co_permissions/model/filters/dict_filter.py
co6co_permissions/model/filters/dict_type_filter.py
co6co_permissions/model/filters/file_param.py
co6co_permissions/model/filters/menu_filter.py
co6co_permissions/model/filters/role_filter.py
co6co_permissions/model/filters/user_filter.py
co6co_permissions/model/filters/user_group_filter.py
co6co_permissions/model/pos/__init__.py
co6co_permissions/model/pos/other.py
co6co_permissions/model/pos/resource.py
co6co_permissions/model/pos/right.py
co6co_permissions/services/__init__.py
co6co_permissions/services/baseCache.py
co6co_permissions/services/bllConfig.py
co6co_permissions/services/configCache.py
co6co_permissions/services/fileService.py
co6co_permissions/view_model/__init__.py
co6co_permissions/view_model/base_view.py
co6co_permissions/view_model/currentUser.py
co6co_permissions/view_model/login.py
co6co_permissions/view_model/menu_view.py
co6co_permissions/view_model/role_view.py
co6co_permissions/view_model/user.py
co6co_permissions/view_model/user_group.py
co6co_permissions/view_model/aop/__init__.py
co6co_permissions/view_model/aop/api_auth.py
co6co_permissions/view_model/aop/api_check.py
co6co_permissions/view_model/aop/authonCache.py
co6co_permissions/view_model/aop/config_aop.py
co6co_permissions/view_model/aop/login_log.py
